[
  {
    "full_name": "yetone/avante.nvim",
    "stargazers_count": 14309,
    "open_issues_count": 185,
    "forks_count": 618
  },
  {
    "full_name": "dotenvx/dotenvx",
    "stargazers_count": 3815,
    "open_issues_count": 12,
    "forks_count": 72
  },
  {
    "full_name": "pomdtr/tweety",
    "stargazers_count": 206,
    "open_issues_count": 4,
    "forks_count": 7
  },
  {
    "full_name": "MONOGRID/gainmap-js",
    "stargazers_count": 126,
    "open_issues_count": 6,
    "forks_count": 8
  },
  {
    "full_name": "ichtrojan/cook",
    "stargazers_count": 30,
    "open_issues_count": 0,
    "forks_count": 5
  },
  {
    "full_name": "lusionltd/WebGL-Scroll-Sync",
    "stargazers_count": 258,
    "open_issues_count": 0,
    "forks_count": 7
  },
  {
    "full_name": "bizarro/2024",
    "stargazers_count": 70,
    "open_issues_count": 0,
    "forks_count": 7
  },
  {
    "full_name": "microsoft/typescript-go",
    "stargazers_count": 20721,
    "open_issues_count": 132,
    "forks_count": 641
  },
  {
    "full_name": "luisdnsantos/awesome-computer-graphics",
    "stargazers_count": 879,
    "open_issues_count": 1,
    "forks_count": 67
  },
  {
    "full_name": "vanjs-org/van",
    "stargazers_count": 4096,
    "open_issues_count": 39,
    "forks_count": 105
  },
  {
    "full_name": "ariedov/android-nvim",
    "stargazers_count": 20,
    "open_issues_count": 2,
    "forks_count": 2
  },
  {
    "full_name": "wojciech-kulik/xcodebuild.nvim",
    "stargazers_count": 987,
    "open_issues_count": 4,
    "forks_count": 27
  },
  {
    "full_name": "q5js/q5.js",
    "stargazers_count": 330,
    "open_issues_count": 17,
    "forks_count": 16
  },
  {
    "full_name": "JoshuaManuel/Karabiner-Elements-Key-List",
    "stargazers_count": 100,
    "open_issues_count": 0,
    "forks_count": 6
  },
  {
    "full_name": "teal-language/tl",
    "stargazers_count": 2478,
    "open_issues_count": 103,
    "forks_count": 131
  },
  {
    "full_name": "voidcosmos/npkill",
    "stargazers_count": 8632,
    "open_issues_count": 26,
    "forks_count": 201
  },
  {
    "full_name": "iamgideonidoko/loft.nvim",
    "stargazers_count": 1,
    "open_issues_count": 0,
    "forks_count": 0
  },
  {
    "full_name": "ghostty-org/ghostty",
    "stargazers_count": 31367,
    "open_issues_count": 191,
    "forks_count": 847
  },
  {
    "full_name": "FradSer/30-days-of-shaders",
    "stargazers_count": 58,
    "open_issues_count": 0,
    "forks_count": 5
  },
  {
    "full_name": "github/copilot.vim",
    "stargazers_count": 10108,
    "open_issues_count": 18,
    "forks_count": 456
  },
  {
    "full_name": "codecrafters-io/build-your-own-x",
    "stargazers_count": 386011,
    "open_issues_count": 384,
    "forks_count": 36004
  },
  {
    "full_name": "google/bundletool",
    "stargazers_count": 3735,
    "open_issues_count": 85,
    "forks_count": 402
  },
  {
    "full_name": "FarazzShaikh/THREE-CustomShaderMaterial",
    "stargazers_count": 1097,
    "open_issues_count": 0,
    "forks_count": 65
  },
  {
    "full_name": "rossant/awesome-math",
    "stargazers_count": 9682,
    "open_issues_count": 15,
    "forks_count": 1007
  },
  {
    "full_name": "donmccurdy/glTF-Transform",
    "stargazers_count": 1604,
    "open_issues_count": 74,
    "forks_count": 157
  },
  {
    "full_name": "expo/orbit",
    "stargazers_count": 568,
    "open_issues_count": 15,
    "forks_count": 28
  },
  {
    "full_name": "kamranahmedse/driver.js",
    "stargazers_count": 24220,
    "open_issues_count": 95,
    "forks_count": 1093
  },
  {
    "full_name": "maxwellito/vivus",
    "stargazers_count": 15373,
    "open_issues_count": 21,
    "forks_count": 1136
  },
  {
    "full_name": "huggingface/transformers.js",
    "stargazers_count": 13766,
    "open_issues_count": 397,
    "forks_count": 932
  },
  {
    "full_name": "nanostores/nanostores",
    "stargazers_count": 6227,
    "open_issues_count": 25,
    "forks_count": 114
  }
]